CHANGES.rst
LICENSE.rst
MANIFEST.in
README.rst
setup.cfg
setup.py
tox.ini
cextern/README.rst
docs/Makefile
docs/conf.py
docs/index.rst
docs/make.bat
docs/_templates/autosummary/base.rst
docs/_templates/autosummary/class.rst
docs/_templates/autosummary/module.rst
docs/padova/index.rst
padova/__init__.py
padova/basereader.py
padova/cmd.py
padova/interface.py
padova/isocdata.py
padova/lfdata.py
padova/resultcache.py
padova/settings.py
padova/utils.py
padova.egg-info/PKG-INFO
padova.egg-info/SOURCES.txt
padova.egg-info/dependency_links.txt
padova.egg-info/requires.txt
padova.egg-info/top_level.txt
padova/data/settings/cmd_2_6.toml
padova/extern/__init__.py
scripts/README.rst