Metadata-Version: 1.1
Name: padova
Version: 0.1.2
Summary: Helpers for using Padova isochrones.
Home-page: http://github.com/jonathansick/padova
Author: Jonathan Sick
Author-email: jonathansick@mac.com
License: MIT
Keywords: astronomy stellarpopulations
Platform: UNKNOWN
Classifier: Development Status :: 4 - Beta
Classifier: Intended Audience :: Science/Research
Classifier: License :: OSI Approved :: MIT License
Classifier: Programming Language :: Python :: 2.7
